easy_email/__init__.py
easy_email/admin.py
easy_email/apps.py
easy_email/enums.py
easy_email/exceptions.py
easy_email/models.py
easy_email/settings.py
easy_email/utils.py
easy_email/validators.py
easy_email/backends/__init__.py
easy_email/loaders/db_template_loader.py
easy_email/migrations/0001_initial.py
easy_email/migrations/__init__.py
easy_email/processors/__init__.py
easy_email/processors/base.py
easy_email/processors/celery.py
easy_email/processors/default.py
django_easy_email-1.0.0.dist-info/LICENSE
django_easy_email-1.0.0.dist-info/METADATA
django_easy_email-1.0.0.dist-info/WHEEL
django_easy_email-1.0.0.dist-info/top_level.txt
django_easy_email-1.0.0.dist-info/RECORD
