Metadata-Version: 2.1
Name: django-easy-email
Version: 1.0.0
Summary: A Django extension designed to streamline email management with powerful templates, scheduling, storage, and more.
Home-page: https://github.com/farhad0085/django-easy-email
Author: Farhad Hossain
Author-email: farhadhossain0085@gmail.com
License: MIT
Classifier: License :: OSI Approved :: MIT License
Classifier: Programming Language :: Python :: 3
Classifier: Programming Language :: Python :: 3.6
License-File: LICENSE
Requires-Dist: django>=3.2
Requires-Dist: filetype>=1.2.0
